swh/graph/cli.py
swh/graph/client.py
swh/graph/config.py
swh/graph/download.py
swh/graph/e2e_check.py
swh/graph/find_context.py
swh/graph/grpc_server.py
swh/graph/http_client.py
swh/graph/http_naive_client.py
swh/graph/http_rpc_server.py
swh/graph/naive_client.py
swh/graph/py.typed
swh/graph/pytest_plugin.py
swh/graph/shell.py
swh/graph/webgraph.py
swh/graph/example_dataset/__init__.py
swh/graph/example_dataset/generate_dataset.py
swh/graph/example_dataset/compressed/example-labelled.ef
swh/graph/example_dataset/compressed/example-labelled.labeloffsets
swh/graph/example_dataset/compressed/example-labelled.labels
swh/graph/example_dataset/compressed/example-labelled.properties
swh/graph/example_dataset/compressed/example-transposed-labelled.ef
swh/graph/example_dataset/compressed/example-transposed-labelled.labeloffsets
swh/graph/example_dataset/compressed/example-transposed-labelled.labels
swh/graph/example_dataset/compressed/example-transposed-labelled.properties
swh/graph/example_dataset/compressed/example-transposed.ef
swh/graph/example_dataset/compressed/example-transposed.graph
swh/graph/example_dataset/compressed/example-transposed.offsets
swh/graph/example_dataset/compressed/example-transposed.properties
swh/graph/example_dataset/compressed/example.edges.count.txt
swh/graph/example_dataset/compressed/example.edges.stats.txt
swh/graph/example_dataset/compressed/example.ef
swh/graph/example_dataset/compressed/example.graph
swh/graph/example_dataset/compressed/example.labels.count.txt
swh/graph/example_dataset/compressed/example.labels.csv.zst
swh/graph/example_dataset/compressed/example.labels.fcl.bytearray
swh/graph/example_dataset/compressed/example.labels.fcl.pointers
swh/graph/example_dataset/compressed/example.labels.fcl.properties
swh/graph/example_dataset/compressed/example.labels.pthash
swh/graph/example_dataset/compressed/example.labels.pthash.order
swh/graph/example_dataset/compressed/example.node2swhid.bin
swh_graph-9.1.0.dist-info/licenses/AUTHORS
swh_graph-9.1.0.dist-info/licenses/LICENSE
swh_graph-9.1.0.dist-info/METADATA
swh_graph-9.1.0.dist-info/WHEEL
swh_graph-9.1.0.dist-info/entry_points.txt
swh_graph-9.1.0.dist-info/top_level.txt
swh_graph-9.1.0.dist-info/RECORD
