Metadata-Version: 2.4
Name: swh.graph
Version: 9.1.0
Summary: Software Heritage graph service
Author-email: Software Heritage developers <swh-devel@inria.fr>
Project-URL: Homepage, https://gitlab.softwareheritage.org/swh/devel/swh-graph
Project-URL: Bug Reports, https://gitlab.softwareheritage.org/swh/devel/swh-graph/-/issues
Project-URL: Funding, https://www.softwareheritage.org/donate
Project-URL: Documentation, https://docs.softwareheritage.org/devel/swh-graph/
Project-URL: Source, https://gitlab.softwareheritage.org/swh/devel/swh-graph.git
Classifier: Programming Language :: Python :: 3
Classifier: Intended Audience :: Developers
Classifier: License :: OSI Approved :: GNU General Public License v3 (GPLv3)
Classifier: Operating System :: OS Independent
Classifier: Development Status :: 3 - Alpha
Requires-Python: >=3.9
License-File: LICENSE
License-File: AUTHORS
Requires-Dist: aiohttp
Requires-Dist: click
Requires-Dist: grpcio-tools>=1.69.0
Requires-Dist: mypy-protobuf
Requires-Dist: protobuf>=5.29.3
Requires-Dist: psutil
Requires-Dist: swh.core[http,s3]>=4.6.0
Requires-Dist: swh.model>=8.1.0
Provides-Extra: export
Requires-Dist: swh.export; extra == "export"
Provides-Extra: luigi
Requires-Dist: datafusion<43.0.0; extra == "luigi"
Requires-Dist: luigi!=3.5.2; extra == "luigi"
Requires-Dist: pyarrow<19.0.0; extra == "luigi"
Requires-Dist: python-magic; extra == "luigi"
Requires-Dist: pyzstd; extra == "luigi"
Requires-Dist: tqdm; extra == "luigi"
Requires-Dist: scancode-toolkit==32.2.1; extra == "luigi"
Requires-Dist: swh.export; extra == "luigi"
Requires-Dist: swh.export[luigi]>=v1.2.0; extra == "luigi"
Provides-Extra: testing
Requires-Dist: pytest>=8.1; extra == "testing"
Requires-Dist: pytest-mock; extra == "testing"
Requires-Dist: pytest-postgresql; extra == "testing"
Requires-Dist: swh.core[testing]>=4.6.0; extra == "testing"
Requires-Dist: grpc-stubs; extra == "testing"
Requires-Dist: pyarrow-stubs; extra == "testing"
Requires-Dist: types-psutil; extra == "testing"
Requires-Dist: types-pyyaml; extra == "testing"
Requires-Dist: types-requests; extra == "testing"
Requires-Dist: types-protobuf; extra == "testing"
Requires-Dist: datafusion<43.0.0; extra == "testing"
Requires-Dist: luigi!=3.5.2; extra == "testing"
Requires-Dist: pyarrow<19.0.0; extra == "testing"
Requires-Dist: python-magic; extra == "testing"
Requires-Dist: pyzstd; extra == "testing"
Requires-Dist: tqdm; extra == "testing"
Requires-Dist: scancode-toolkit==32.2.1; extra == "testing"
Requires-Dist: swh.export; extra == "testing"
Requires-Dist: swh.export[luigi]>=v1.2.0; extra == "testing"
Dynamic: license-file
